{"cameraMode":{"drawMode":0,"name":"Shaded","section":"Shading Mode"},"sceneLighting":true,"audioPlay":false,"sceneViewState":{"m_AlwaysRefresh":false,"showFog":true,"showSkybox":true,"showFlares":true,"showImageEffects":true,"showParticleSystems":true,"showVisualEffectGraphs":true,"m_FxEnabled":true},"in2DMode":false,"pivot":{"x":-36.8345947265625,"y":-15.108968734741211,"z":91.68063354492188},"rotation":{"x":-0.09852826595306397,"y":0.27021118998527529,"z":-0.02802177704870701,"w":-0.9574081897735596},"size":40.293113708496097,"orthographic":false}